<help>
  <overview>Allows a bot admin to administrate users via irc</overview>
  <command name="useradmin">useradmin [add|remove|hostmasks|addhostmask|removehostmask|password|addop|removeop|addadmin|removeadmin] username [hostmask|password|channel]<br/>add - adds a user<br/>remove - removes a user<br/>hostmasks - lists a user's hostmasks<br/>addhostmask - adds a hostmasks to a user's list of hostmasks<br/>delhostmask - removes a hostmask from a user's list of hostmasks<br/>password - changes a user's password<br/>addop - adds a user as an op for a channel<br/>removeop - removes a user from the list of ops for a channel<br/>addadmin - adds a user as a bot admin<br/>removeadmin - removes a user from the list of bot admins</command>
</help>
